{
  "status": "foundAlternatives",
  "annotatedAlternativeRoutes": [
    {
      "alternativeRouteParts": [
        {
          "from": { "evaNumber": "8098263", "name": "München Hbf (tief)" },
          "replacementTransports": [
            {
              "begin": "2024-10-04T15:28:00Z",
              "end": "2024-10-04T16:07:00Z",
              "line": {
                "administrationID": "800725",
                "category": "S",
                "line": "2"
              },
              "type": "UNKNOWN"
            }
          ],
          "to": { "evaNumber": "8004775", "name": "Petershausen(Obb)" }
        },
        {
          "from": { "evaNumber": "8004775", "name": "Petershausen(Obb)" },
          "replacementTransports": [
            {
              "begin": "2024-10-04T16:24:00Z",
              "end": "2024-10-04T16:52:00Z",
              "line": {
                "administrationID": "800765",
                "category": "RE",
                "line": "1"
              },
              "type": "UNKNOWN"
            }
          ],
          "to": { "evaNumber": "8000183", "name": "Ingolstadt Hbf" }
        }
      ],
      "intervals": "Fr 15:25-17:25",
      "estimatedTravelTime": 5220.0,
      "headway": 3600.0,
      "begin": "2024-10-04T15:25:00Z",
      "end": "2024-10-04T17:25:00Z",
      "geom": {
        "type": "FeatureCollection",
        "features": [
          {
            "type": "Feature",
            "geometry": {
              "type": "LineString",
              "coordinates": [
                [11.5588457, 48.1409162],
                [11.5544205, 48.1412423],
                [11.5537307, 48.1412701],
                [11.5517861, 48.1412606],
                [11.546463, 48.1416627],
                [11.5445274, 48.1418299],
                [11.5397033, 48.1421956],
                [11.5385243, 48.1422741],
                [11.5372982, 48.1423385],
                [11.534628, 48.1424488],
                [11.53039, 48.1425723],
                [11.5298841, 48.1426001],
                [11.5192344536, 48.1433788832],
                [11.5184829, 48.1434151],
                [11.5177697, 48.1434236],
                [11.5170806, 48.1434129],
                [11.5137338, 48.1432722],
                [11.5126055, 48.1432838],
                [11.5117018, 48.1433326],
                [11.5108206, 48.1433983],
                [11.4980989, 48.1447378],
                [11.4953972, 48.1450119],
                [11.4927359, 48.1453352],
                [11.4921554, 48.1454517],
                [11.4915475, 48.1456006],
                [11.4912453, 48.1456906],
                [11.4909565, 48.1457914],
                [11.4903418, 48.1460357],
                [11.489931, 48.146225],
                [11.4893904, 48.1465223],
                [11.4887432, 48.1469485],
                [11.4876514, 48.1476337],
                [11.485475, 48.1495367],
                [11.484459, 48.1503991],
                [11.484101, 48.1507313],
                [11.4838039, 48.1510411],
                [11.4834714, 48.1514254],
                [11.483303, 48.1516406],
                [11.4829764, 48.1521161],
                [11.4825731, 48.1527657],
                [11.4823892, 48.1530952],
                [11.4820397, 48.1537678],
                [11.481819, 48.1542546],
                [11.4816761, 48.1545988],
                [11.4815116, 48.1550699],
                [11.4811456, 48.1562816],
                [11.4808017, 48.1573639],
                [11.4805465312, 48.1580984311],
                [11.48033, 48.1586986],
                [11.4794382, 48.1609692],
                [11.4785667, 48.1634074],
                [11.4782373971, 48.1642703285],
                [11.4778635, 48.1652039],
                [11.4771698, 48.1668303],
                [11.4766476, 48.1680961],
                [11.473772, 48.1754688],
                [11.4729192311, 48.1777226013],
                [11.4717443, 48.1806151],
                [11.4713435, 48.1817551],
                [11.4708502, 48.1832267],
                [11.469955, 48.1859631],
                [11.4694753, 48.1873108],
                [11.4677019, 48.1918038],
                [11.4667488, 48.1941701],
                [11.4664422, 48.1949124],
                [11.4652625, 48.1976066],
                [11.4647396, 48.1988505],
                [11.46396, 48.2007796],
                [11.4628818, 48.2033932],
                [11.4597759667, 48.2112596881],
                [11.458975, 48.2133299],
                [11.4576365, 48.2169731],
                [11.4567785, 48.2191648],
                [11.4551953186, 48.2231632753],
                [11.4532895, 48.2280231],
                [11.4528008, 48.2292269],
                [11.4522503, 48.2305095],
                [11.4515676, 48.232197],
                [11.4475348, 48.2425057],
                [11.4472518, 48.2432824],
                [11.4468406, 48.244572],
                [11.4465661, 48.245556],
                [11.4461932, 48.2470601],
                [11.4460282, 48.2476746],
                [11.4456376, 48.2495954],
                [11.4449549, 48.252856],
                [11.4445187961, 48.2547164079],
                [11.4441865, 48.2560516],
                [11.4437524, 48.257553],
                [11.4428212, 48.2605495],
                [11.4425789, 48.2614196],
                [11.4424471, 48.2619638],
                [11.4423025, 48.2627878],
                [11.4422698, 48.2630541],
                [11.4422297, 48.2635467],
                [11.4422164, 48.2638361],
                [11.4422158, 48.2642068],
                [11.4422281, 48.2645746],
                [11.4422541, 48.2649409],
                [11.4422942, 48.2652816],
                [11.442396, 48.2658983],
                [11.4424487, 48.2661473],
                [11.4426383, 48.266869],
                [11.4430048, 48.268034],
                [11.4439219, 48.2708105],
                [11.4441329, 48.2713891],
                [11.4444616, 48.2721907],
                [11.4446491, 48.2725928],
                [11.4448805, 48.2730324],
                [11.4451856, 48.273551],
                [11.4455223, 48.2740805],
                [11.4459531, 48.2746773],
                [11.4464306, 48.2752604],
                [11.4469428, 48.2758274],
                [11.4474032, 48.2762917],
                [11.4478849, 48.2767455],
                [11.4484022, 48.2772065],
                [11.4511037, 48.2794722],
                [11.4516035, 48.2799211],
                [11.4521016, 48.2803934],
                [11.4527286, 48.281037],
                [11.4532223, 48.2816118],
                [11.4535497, 48.2820262],
                [11.4538642, 48.2824472],
                [11.4542233, 48.2829847],
                [11.4545516, 48.2835321],
                [11.4547303, 48.2838636],
                [11.4550495, 48.2845284],
                [11.4552843, 48.2851077],
                [11.4555054, 48.2857475],
                [11.455682, 48.286392],
                [11.4557958, 48.2869281],
                [11.4558741, 48.287459],
                [11.4559265, 48.287965],
                [11.4559506, 48.2884713],
                [11.4559444, 48.2891459],
                [11.4558954, 48.2897531],
                [11.4558158, 48.2904111],
                [11.4556988162, 48.2911424688],
                [11.4554017, 48.2928511],
                [11.4553367, 48.2932832],
                [11.4552598, 48.2939566],
                [11.4552209, 48.2945803],
                [11.4552266, 48.2955078],
                [11.4552849, 48.2962164],
                [11.4553272, 48.2965568],
                [11.4554623, 48.2973467],
                [11.4561201, 48.3002137],
                [11.4562196, 48.3007325],
                [11.4563066, 48.3014045],
                [11.4563437, 48.3018619],
                [11.4563615, 48.3023165],
                [11.4563592, 48.3029389],
                [11.4563397, 48.3033549],
                [11.4563018, 48.3037683],
                [11.4562431, 48.3042287],
                [11.4561066, 48.3050225],
                [11.4560303, 48.3053551],
                [11.4558281, 48.3060465],
                [11.4556557, 48.306556],
                [11.4554943, 48.3069805],
                [11.4552287, 48.3075769],
                [11.4549478, 48.3081791],
                [11.4546034, 48.3088416],
                [11.4463175, 48.3242819],
                [11.4460117, 48.3249259],
                [11.4458304, 48.3253628],
                [11.445576, 48.3261011],
                [11.4454495, 48.3265521],
                [11.4453807, 48.3268418],
                [11.4452919, 48.3272803],
                [11.4452284, 48.3277242],
                [11.4451391, 48.3288784],
                [11.4450977, 48.3298812],
                [11.4450716, 48.3308929],
                [11.4449927, 48.3326772],
                [11.4445675, 48.3438836],
                [11.4444539, 48.3458656],
                [11.444329, 48.3476988],
                [11.4440793, 48.354043],
                [11.4440078, 48.3560883],
                [11.444042, 48.3568913],
                [11.4440839, 48.3574358],
                [11.4442587, 48.3583705],
                [11.4444188, 48.3589629],
                [11.4448334, 48.3601095],
                [11.4465584, 48.3641668],
                [11.4470688, 48.3653378],
                [11.4473737, 48.3659551],
                [11.4478761, 48.3668339],
                [11.4481879, 48.3672942],
                [11.4486346, 48.3678908],
                [11.4492128, 48.3685698],
                [11.4558339, 48.3758212],
                [11.4582914, 48.3785284],
                [11.4589188, 48.3792682],
                [11.4595192, 48.3800538],
                [11.4599931, 48.3807594],
                [11.4604773, 48.3816135],
                [11.4606951, 48.3820724],
                [11.4608949, 48.3825293],
                [11.4611566, 48.383223],
                [11.461378, 48.3839175],
                [11.4616914, 48.3850197],
                [11.4634845, 48.3917579],
                [11.4636573, 48.3924619],
                [11.4637513, 48.3930292],
                [11.4638237, 48.3935647],
                [11.46387, 48.3941426],
                [11.463882, 48.394629],
                [11.4638473, 48.3954123],
                [11.4632334, 48.401031],
                [11.4631706, 48.4017415],
                [11.4631278, 48.4026113],
                [11.463134, 48.4031923],
                [11.4631521, 48.4035037],
                [11.4631806, 48.4038334],
                [11.4632888, 48.4045789],
                [11.4634713, 48.4053477],
                [11.4635952, 48.4057658],
                [11.4638565, 48.4064671],
                [11.4641485, 48.4071226],
                [11.4644675, 48.4077154],
                [11.4649601, 48.4084947],
                [11.4652158, 48.4088676],
                [11.4658588, 48.4096731],
                [11.4660412, 48.4098859],
                [11.4666412, 48.4105192],
                [11.4670639, 48.4109232],
                [11.4678586, 48.4116174],
                [11.4688149, 48.4123824],
                [11.4699989218, 48.4132964401]
              ]
            },
            "properties": {
              "id": 0,
              "route_index": 0,
              "from_eva": "8098263",
              "to_eva": "8004775",
              "line": "2",
              "category": "S",
              "from_name": "München Hbf (tief)",
              "to_name": "Petershausen(Obb)",
              "begin": "2024-10-04T15:28:00Z",
              "end": "2024-10-04T16:07:00Z",
              "estimated_travel_time_total": "PT1H27M"
            }
          },
          {
            "type": "Feature",
            "geometry": {
              "type": "LineString",
              "coordinates": [
                [11.4699989218, 48.4132964401],
                [11.4717079, 48.4146088],
                [11.4725569, 48.4152964],
                [11.4731152, 48.4157839],
                [11.4737155, 48.4163477],
                [11.4742053, 48.4168589],
                [11.4746896, 48.4174157],
                [11.475104, 48.4179336],
                [11.4754605, 48.4184404],
                [11.4757969, 48.4189528],
                [11.4760552, 48.4193842],
                [11.476283, 48.4198148],
                [11.4764479, 48.420168],
                [11.4766644, 48.4205957],
                [11.4768443, 48.4210156],
                [11.4772524, 48.4221294],
                [11.4774302, 48.4226837],
                [11.4776524, 48.4236155],
                [11.4777156, 48.4239957],
                [11.4777939, 48.4246165],
                [11.4778486, 48.4254699],
                [11.4778891, 48.4270437],
                [11.4779042, 48.4287164],
                [11.4779452, 48.430839],
                [11.4779789, 48.4314398],
                [11.4780451, 48.4320281],
                [11.4781594, 48.4326095],
                [11.478305, 48.4331882],
                [11.4784475, 48.4336145],
                [11.4786052, 48.434046],
                [11.4787006, 48.4342718],
                [11.4789437, 48.4347875],
                [11.4792557, 48.4353759],
                [11.4794871, 48.4357573],
                [11.4797302, 48.4361135],
                [11.4802274, 48.4367838],
                [11.4807791, 48.4374388],
                [11.4810781, 48.4377524],
                [11.4813955, 48.4380686],
                [11.4823137, 48.4388775],
                [11.4832983, 48.4396475],
                [11.4888313, 48.4438186],
                [11.4903644, 48.4449865],
                [11.4910662, 48.4455594],
                [11.4916781, 48.4461079],
                [11.4922377, 48.446678],
                [11.4925897, 48.4470685],
                [11.4929126, 48.4474553],
                [11.493383, 48.448075],
                [11.4953568, 48.4508963],
                [11.4959425, 48.4516411],
                [11.4961297, 48.4518618],
                [11.4965322, 48.4523034],
                [11.4969641, 48.4527456],
                [11.4974388, 48.4531775],
                [11.4982063, 48.4538084],
                [11.4990238, 48.4544115],
                [11.5024095, 48.4566802],
                [11.5031616, 48.4572055],
                [11.5037993, 48.4576897],
                [11.5041724, 48.4579953],
                [11.5047153, 48.4584773],
                [11.5052564, 48.4590087],
                [11.5056927, 48.4594848],
                [11.5060706, 48.4599272],
                [11.5064309, 48.4603874],
                [11.507716, 48.462092],
                [11.5079876, 48.4624664],
                [11.5085065, 48.4632198],
                [11.5088326, 48.4637632],
                [11.5091241, 48.4643078],
                [11.5093216, 48.4647263],
                [11.5095618, 48.465333],
                [11.5097615, 48.465968],
                [11.5098902, 48.4664879],
                [11.5100216, 48.4672003],
                [11.5100845, 48.4679262],
                [11.5101297, 48.4691688],
                [11.5103905, 48.4789459],
                [11.510426, 48.4797626],
                [11.5104815, 48.4803365],
                [11.5105855, 48.4811188],
                [11.5107125, 48.4818488],
                [11.5111543, 48.4838553],
                [11.5113816, 48.4849624],
                [11.5130543, 48.4926118],
                [11.513189, 48.493299],
                [11.5132588, 48.4937899],
                [11.5132944, 48.4941604],
                [11.5133225, 48.4946706],
                [11.5133111, 48.4952688],
                [11.5132758, 48.4956826],
                [11.5132038, 48.4962077],
                [11.5131025, 48.496726],
                [11.5129953, 48.4971359],
                [11.512699, 48.4981465],
                [11.5118573, 48.5008102],
                [11.511336, 48.5025737],
                [11.5107187, 48.5045496],
                [11.5104106, 48.5056293],
                [11.5102595, 48.5062801],
                [11.5101344, 48.5069375],
                [11.5100006, 48.5078294],
                [11.5099368, 48.5084134],
                [11.5098839, 48.5092425],
                [11.5098703, 48.5098483],
                [11.5098894, 48.5108435],
                [11.5099619, 48.5117738],
                [11.5101997, 48.5134177],
                [11.5105196, 48.515147],
                [11.5110271, 48.5178069],
                [11.5114481, 48.5199406],
                [11.5120927, 48.5233703],
                [11.5123486, 48.5246768],
                [11.5126251, 48.5257446],
                [11.5127623, 48.526149],
                [11.5129764, 48.5266819],
                [11.5133594, 48.5274752],
                [11.5135056, 48.5277453],
                [11.5137446, 48.5281449],
                [11.5141324, 48.5287516],
                [11.5151518, 48.5302769],
                [11.5155119, 48.5308689],
                [11.5159185, 48.5316157],
                [11.5160629, 48.5319164],
                [11.5162798, 48.5324306],
                [11.5164678, 48.5330245],
                [11.5166192, 48.5335956],
                [11.5167318, 48.5342249],
                [11.5167878, 48.5345866],
                [11.5170592, 48.5366558],
                [11.517167, 48.5375906],
                [11.5174044, 48.5391749],
                [11.5174851, 48.539568],
                [11.517561, 48.5398714],
                [11.5178659, 48.5408548],
                [11.5181046, 48.5414197],
                [11.5182259, 48.5416756],
                [11.518435, 48.5420636],
                [11.5186839, 48.5424798],
                [11.5189247, 48.5428572],
                [11.5192341, 48.5432965],
                [11.519712, 48.5439018],
                [11.519902, 48.5441167],
                [11.520391, 48.5446363],
                [11.5206331, 48.5448748],
                [11.5215826, 48.5457629],
                [11.5235004, 48.5475896],
                [11.5249948, 48.5489927],
                [11.5281361, 48.5519787],
                [11.5389353, 48.5621969],
                [11.5420812, 48.5651956],
                [11.5468129, 48.5696592],
                [11.5494571, 48.5721769],
                [11.5545456, 48.5769738],
                [11.5638163, 48.5857459],
                [11.5648136, 48.5867204],
                [11.5653205, 48.5872634],
                [11.5655353, 48.5875103],
                [11.5659066, 48.5879708],
                [11.5662256, 48.5884026],
                [11.566779, 48.5892035],
                [11.5708933, 48.5953393],
                [11.5715343, 48.5963154],
                [11.5720706, 48.5972382],
                [11.572306, 48.5977088],
                [11.5725115, 48.5981896],
                [11.5726858, 48.598673],
                [11.5727737, 48.5989644],
                [11.5728934, 48.5993984],
                [11.5729487, 48.5996512],
                [11.5730402, 48.600158],
                [11.5731019, 48.6006724],
                [11.5731376, 48.601159],
                [11.573618, 48.6120559],
                [11.5736806, 48.6130041],
                [11.5741122, 48.6231523],
                [11.5741226, 48.6238597],
                [11.5741108, 48.6242029],
                [11.5740655, 48.6247228],
                [11.5739831, 48.6251668],
                [11.573864, 48.6256288],
                [11.5737857, 48.6258736],
                [11.573575, 48.626439],
                [11.573494, 48.6266245],
                [11.5733054, 48.6269988],
                [11.5731028, 48.6273689],
                [11.5726561, 48.6280582],
                [11.5720761, 48.6287747],
                [11.5716017, 48.6292724],
                [11.5709813, 48.6298216],
                [11.5702841, 48.6303678],
                [11.5697315, 48.6307545],
                [11.5694424, 48.6309356],
                [11.5685448, 48.6314523],
                [11.5606461, 48.6355959],
                [11.5597733, 48.6360998],
                [11.5586844, 48.636808],
                [11.5493037, 48.643183],
                [11.5485877, 48.6436504],
                [11.5480294, 48.6439931],
                [11.5474523, 48.6443164],
                [11.5469991, 48.6445503],
                [11.5465308, 48.644777],
                [11.5459999, 48.645007],
                [11.5454291, 48.6452322],
                [11.5445956, 48.6455263],
                [11.5437224, 48.645786],
                [11.5425816, 48.6460711],
                [11.5414178, 48.6463194],
                [11.535526, 48.6475239],
                [11.5251841, 48.6495719],
                [11.4748507, 48.6596578],
                [11.4738164, 48.6598726],
                [11.4725174, 48.6601765],
                [11.4715283, 48.6604449],
                [11.4710408, 48.6605945],
                [11.4703012, 48.6608427],
                [11.4695883, 48.6611073],
                [11.4690708, 48.6613201],
                [11.4680749, 48.6617615],
                [11.467151, 48.6622391],
                [11.4667131, 48.6624894],
                [11.4662893, 48.6627478],
                [11.4657026, 48.6631285],
                [11.4651593, 48.6635154],
                [11.4642678, 48.6642248],
                [11.4636232, 48.6648123],
                [11.4630452, 48.6654199],
                [11.4626722, 48.6658545],
                [11.4622734, 48.6663477],
                [11.4619375, 48.6668341],
                [11.4616317, 48.6673331],
                [11.4613938, 48.6677587],
                [11.4612751, 48.6679966],
                [11.4608322, 48.6691257],
                [11.4606518, 48.6697268],
                [11.4605119, 48.6704432],
                [11.4604485, 48.6708677],
                [11.4603891, 48.6713881],
                [11.4603412, 48.6719423],
                [11.4599556, 48.6779812],
                [11.4598855, 48.6787463],
                [11.4597306, 48.6796101],
                [11.4596327, 48.6800581],
                [11.4591028, 48.6822689],
                [11.458069, 48.6866907],
                [11.4558709, 48.6958908],
                [11.4556203, 48.6968707],
                [11.4555115, 48.6972518],
                [11.4552788, 48.6979891],
                [11.4551554, 48.6983409],
                [11.4504697, 48.7105624],
                [11.4496313, 48.7127795],
                [11.4473266, 48.718743],
                [11.4463841, 48.7212697],
                [11.4454894, 48.7237253],
                [11.4449152, 48.7252534],
                [11.4433226, 48.7292425],
                [11.4431505, 48.7297068],
                [11.4422116, 48.7319998],
                [11.4417647, 48.7331284],
                [11.4374088, 48.7444412]
              ]
            },
            "properties": {
              "id": 1,
              "route_index": 0,
              "from_eva": "8004775",
              "to_eva": "8000183",
              "line": "1",
              "category": "RE",
              "from_name": "Petershausen(Obb)",
              "to_name": "Ingolstadt Hbf",
              "begin": "2024-10-04T16:24:00Z",
              "end": "2024-10-04T16:52:00Z",
              "estimated_travel_time_total": "PT1H27M"
            }
          }
        ]
      }
    },
    {
      "alternativeRouteParts": [
        {
          "from": { "evaNumber": "8000261", "name": "München Hbf" },
          "replacementTransports": [
            {
              "begin": "2024-10-04T15:10:00Z",
              "end": "2024-10-04T16:01:00Z",
              "line": {
                "administrationID": "800765",
                "category": "RE",
                "line": "1"
              },
              "type": "UNKNOWN"
            }
          ],
          "to": { "evaNumber": "8000183", "name": "Ingolstadt Hbf" }
        }
      ],
      "intervals": "Fr 15:09",
      "estimatedTravelTime": 3120.0,
      "headway": null,
      "begin": "2024-10-04T15:09:00Z",
      "end": "2024-10-04T15:09:00Z",
      "geom": {
        "type": "FeatureCollection",
        "features": [
          {
            "type": "Feature",
            "geometry": {
              "type": "LineString",
              "coordinates": [
                [11.5558051, 48.1414745],
                [11.5534692, 48.141645],
                [11.5501545, 48.1416478],
                [11.5469908, 48.1418817],
                [11.5460811, 48.1419746],
                [11.5451791, 48.1420443],
                [11.5411193, 48.1423439],
                [11.5395187, 48.1424333],
                [11.538016, 48.142504],
                [11.5375682, 48.1425107],
                [11.5359143, 48.1424819],
                [11.5355082, 48.1424865],
                [11.5328491, 48.1425778],
                [11.5324064, 48.1425811],
                [11.5316184, 48.1425473],
                [11.5311354, 48.1425494],
                [11.53039, 48.1425723],
                [11.5298841, 48.1426001],
                [11.5192344536, 48.1433788832],
                [11.5184829, 48.1434151],
                [11.5177697, 48.1434236],
                [11.5170806, 48.1434129],
                [11.5137338, 48.1432722],
                [11.5126055, 48.1432838],
                [11.5117018, 48.1433326],
                [11.5108206, 48.1433983],
                [11.4980989, 48.1447378],
                [11.4953972, 48.1450119],
                [11.4927359, 48.1453352],
                [11.4921554, 48.1454517],
                [11.4915475, 48.1456006],
                [11.4912453, 48.1456906],
                [11.4909565, 48.1457914],
                [11.4903418, 48.1460357],
                [11.489931, 48.146225],
                [11.4893904, 48.1465223],
                [11.4887432, 48.1469485],
                [11.4876514, 48.1476337],
                [11.485475, 48.1495367],
                [11.484459, 48.1503991],
                [11.484101, 48.1507313],
                [11.4838039, 48.1510411],
                [11.4834714, 48.1514254],
                [11.483303, 48.1516406],
                [11.4829764, 48.1521161],
                [11.4825731, 48.1527657],
                [11.4823892, 48.1530952],
                [11.4820397, 48.1537678],
                [11.481819, 48.1542546],
                [11.4816761, 48.1545988],
                [11.4815116, 48.1550699],
                [11.4811456, 48.1562816],
                [11.4808017, 48.1573639],
                [11.4805465312, 48.1580984311],
                [11.48033, 48.1586986],
                [11.4794382, 48.1609692],
                [11.4785667, 48.1634074],
                [11.4782373971, 48.1642703285],
                [11.4778635, 48.1652039],
                [11.4771698, 48.1668303],
                [11.4766476, 48.1680961],
                [11.473772, 48.1754688],
                [11.4729192311, 48.1777226013],
                [11.4717443, 48.1806151],
                [11.4713435, 48.1817551],
                [11.4708502, 48.1832267],
                [11.469955, 48.1859631],
                [11.4694753, 48.1873108],
                [11.4677019, 48.1918038],
                [11.4667488, 48.1941701],
                [11.4664422, 48.1949124],
                [11.4652625, 48.1976066],
                [11.4647396, 48.1988505],
                [11.46396, 48.2007796],
                [11.4628818, 48.2033932],
                [11.4597759667, 48.2112596881],
                [11.458975, 48.2133299],
                [11.4576365, 48.2169731],
                [11.4567785, 48.2191648],
                [11.4551953186, 48.2231632753],
                [11.4532895, 48.2280231],
                [11.4528008, 48.2292269],
                [11.4522503, 48.2305095],
                [11.4515676, 48.232197],
                [11.4475348, 48.2425057],
                [11.4472518, 48.2432824],
                [11.4468406, 48.244572],
                [11.4465661, 48.245556],
                [11.4461932, 48.2470601],
                [11.4460282, 48.2476746],
                [11.4456376, 48.2495954],
                [11.4449549, 48.252856],
                [11.4445187961, 48.2547164079],
                [11.4441865, 48.2560516],
                [11.4437524, 48.257553],
                [11.4428212, 48.2605495],
                [11.4425789, 48.2614196],
                [11.4424471, 48.2619638],
                [11.4423351, 48.2625737],
                [11.4422698, 48.2630541],
                [11.4422297, 48.2635467],
                [11.4422164, 48.2638361],
                [11.4422158, 48.2642068],
                [11.4422281, 48.2645746],
                [11.4422541, 48.2649409],
                [11.4422942, 48.2652816],
                [11.442396, 48.2658983],
                [11.4424487, 48.2661473],
                [11.4426383, 48.266869],
                [11.4430048, 48.268034],
                [11.4439219, 48.2708105],
                [11.4441329, 48.2713891],
                [11.4444616, 48.2721907],
                [11.4446491, 48.2725928],
                [11.4448805, 48.2730324],
                [11.4451856, 48.273551],
                [11.4455223, 48.2740805],
                [11.4459531, 48.2746773],
                [11.4464306, 48.2752604],
                [11.4469428, 48.2758274],
                [11.4474032, 48.2762917],
                [11.4478849, 48.2767455],
                [11.4484022, 48.2772065],
                [11.4511037, 48.2794722],
                [11.4516035, 48.2799211],
                [11.4521016, 48.2803934],
                [11.4524467, 48.2807407],
                [11.4527286, 48.281037],
                [11.4529916, 48.2813344],
                [11.4535497, 48.2820262],
                [11.4538642, 48.2824472],
                [11.4542233, 48.2829847],
                [11.4545516, 48.2835321],
                [11.4547303, 48.2838636],
                [11.4550495, 48.2845284],
                [11.4552843, 48.2851077],
                [11.4555054, 48.2857475],
                [11.455682, 48.286392],
                [11.4557958, 48.2869281],
                [11.4558741, 48.287459],
                [11.4559265, 48.287965],
                [11.4559506, 48.2884713],
                [11.4559444, 48.2891459],
                [11.4558954, 48.2897531],
                [11.4558158, 48.2904111],
                [11.4556988162, 48.2911424688],
                [11.4554017, 48.2928511],
                [11.4553367, 48.2932832],
                [11.4552598, 48.2939566],
                [11.4552209, 48.2945803],
                [11.4552266, 48.2955078],
                [11.4552849, 48.2962164],
                [11.4553272, 48.2965568],
                [11.4554623, 48.2973467],
                [11.4561201, 48.3002137],
                [11.4562196, 48.3007325],
                [11.4563066, 48.3014045],
                [11.4563437, 48.3018619],
                [11.4563615, 48.3023165],
                [11.4563592, 48.3029389],
                [11.4563397, 48.3033549],
                [11.4563018, 48.3037683],
                [11.4562431, 48.3042287],
                [11.4561066, 48.3050225],
                [11.4560303, 48.3053551],
                [11.4559358, 48.305701],
                [11.4556557, 48.306556],
                [11.4554943, 48.3069805],
                [11.4552287, 48.3075769],
                [11.4549478, 48.3081791],
                [11.4546034, 48.3088416],
                [11.4463175, 48.3242819],
                [11.4460117, 48.3249259],
                [11.4458304, 48.3253628],
                [11.445576, 48.3261011],
                [11.4454495, 48.3265521],
                [11.4453807, 48.3268418],
                [11.4452919, 48.3272803],
                [11.4452284, 48.3277242],
                [11.4451391, 48.3288784],
                [11.4450977, 48.3298812],
                [11.4450716, 48.3308929],
                [11.4449927, 48.3326772],
                [11.4445675, 48.3438836],
                [11.4444539, 48.3458656],
                [11.444329, 48.3476988],
                [11.4440793, 48.354043],
                [11.4440078, 48.3560883],
                [11.444042, 48.3568913],
                [11.4440839, 48.3574358],
                [11.4442587, 48.3583705],
                [11.4444188, 48.3589629],
                [11.4448334, 48.3601095],
                [11.4465584, 48.3641668],
                [11.4470688, 48.3653378],
                [11.4473737, 48.3659551],
                [11.4478761, 48.3668339],
                [11.4481879, 48.3672942],
                [11.4486346, 48.3678908],
                [11.4492128, 48.3685698],
                [11.4558339, 48.3758212],
                [11.4582914, 48.3785284],
                [11.4589188, 48.3792682],
                [11.4595192, 48.3800538],
                [11.4599931, 48.3807594],
                [11.4604773, 48.3816135],
                [11.4606951, 48.3820724],
                [11.4608949, 48.3825293],
                [11.4611566, 48.383223],
                [11.461378, 48.3839175],
                [11.4616914, 48.3850197],
                [11.4634845, 48.3917579],
                [11.4636573, 48.3924619],
                [11.4637513, 48.3930292],
                [11.4638237, 48.3935647],
                [11.46387, 48.3941426],
                [11.463882, 48.394629],
                [11.4638473, 48.3954123],
                [11.4632334, 48.401031],
                [11.4631706, 48.4017415],
                [11.4631278, 48.4026113],
                [11.463134, 48.4031923],
                [11.4631521, 48.4035037],
                [11.4631806, 48.4038334],
                [11.4632888, 48.4045789],
                [11.4634713, 48.4053477],
                [11.4635952, 48.4057658],
                [11.4638565, 48.4064671],
                [11.4641485, 48.4071226],
                [11.4644675, 48.4077154],
                [11.4649601, 48.4084947],
                [11.4652158, 48.4088676],
                [11.4654835, 48.4092136],
                [11.4660412, 48.4098859],
                [11.4666412, 48.4105192],
                [11.4670639, 48.4109232],
                [11.4678586, 48.4116174],
                [11.4688149, 48.4123824],
                [11.4717079, 48.4146088],
                [11.4725569, 48.4152964],
                [11.4731152, 48.4157839],
                [11.4737155, 48.4163477],
                [11.4742053, 48.4168589],
                [11.4746896, 48.4174157],
                [11.475104, 48.4179336],
                [11.4754605, 48.4184404],
                [11.4757969, 48.4189528],
                [11.4760552, 48.4193842],
                [11.476283, 48.4198148],
                [11.4764479, 48.420168],
                [11.4766644, 48.4205957],
                [11.4768443, 48.4210156],
                [11.4772524, 48.4221294],
                [11.4774302, 48.4226837],
                [11.4776524, 48.4236155],
                [11.4777156, 48.4239957],
                [11.4777939, 48.4246165],
                [11.4778486, 48.4254699],
                [11.4778891, 48.4270437],
                [11.4779042, 48.4287164],
                [11.4779452, 48.430839],
                [11.4779789, 48.4314398],
                [11.4780451, 48.4320281],
                [11.4781594, 48.4326095],
                [11.478305, 48.4331882],
                [11.4784475, 48.4336145],
                [11.4786052, 48.434046],
                [11.4787006, 48.4342718],
                [11.4789437, 48.4347875],
                [11.4792557, 48.4353759],
                [11.4794871, 48.4357573],
                [11.4797302, 48.4361135],
                [11.4802274, 48.4367838],
                [11.4807791, 48.4374388],
                [11.4813955, 48.4380686],
                [11.481926, 48.4385441],
                [11.4823137, 48.4388775],
                [11.4832983, 48.4396475],
                [11.4888313, 48.4438186],
                [11.4903644, 48.4449865],
                [11.4910662, 48.4455594],
                [11.4916781, 48.4461079],
                [11.4922377, 48.446678],
                [11.4925897, 48.4470685],
                [11.4929126, 48.4474553],
                [11.493383, 48.448075],
                [11.4953568, 48.4508963],
                [11.4959425, 48.4516411],
                [11.4961297, 48.4518618],
                [11.4965322, 48.4523034],
                [11.4969641, 48.4527456],
                [11.4974388, 48.4531775],
                [11.4982063, 48.4538084],
                [11.4990238, 48.4544115],
                [11.5024095, 48.4566802],
                [11.5031616, 48.4572055],
                [11.5037993, 48.4576897],
                [11.5041724, 48.4579953],
                [11.5047153, 48.4584773],
                [11.5052564, 48.4590087],
                [11.5056927, 48.4594848],
                [11.5060706, 48.4599272],
                [11.5064309, 48.4603874],
                [11.507716, 48.462092],
                [11.5079876, 48.4624664],
                [11.5085065, 48.4632198],
                [11.5088326, 48.4637632],
                [11.5091241, 48.4643078],
                [11.5093216, 48.4647263],
                [11.5095618, 48.465333],
                [11.5097615, 48.465968],
                [11.5098902, 48.4664879],
                [11.5100216, 48.4672003],
                [11.5100845, 48.4679262],
                [11.5101297, 48.4691688],
                [11.5103905, 48.4789459],
                [11.510426, 48.4797626],
                [11.5104815, 48.4803365],
                [11.5105855, 48.4811188],
                [11.5107125, 48.4818488],
                [11.5111543, 48.4838553],
                [11.5113816, 48.4849624],
                [11.5130543, 48.4926118],
                [11.513189, 48.493299],
                [11.5132588, 48.4937899],
                [11.5132944, 48.4941604],
                [11.5133225, 48.4946706],
                [11.5133111, 48.4952688],
                [11.5132758, 48.4956826],
                [11.5132038, 48.4962077],
                [11.5131025, 48.496726],
                [11.5129953, 48.4971359],
                [11.512699, 48.4981465],
                [11.5118573, 48.5008102],
                [11.511336, 48.5025737],
                [11.5107187, 48.5045496],
                [11.5104106, 48.5056293],
                [11.5102595, 48.5062801],
                [11.5101344, 48.5069375],
                [11.5100006, 48.5078294],
                [11.5099368, 48.5084134],
                [11.5098839, 48.5092425],
                [11.5098703, 48.5098483],
                [11.5098894, 48.5108435],
                [11.5099619, 48.5117738],
                [11.5101997, 48.5134177],
                [11.5105196, 48.515147],
                [11.5110271, 48.5178069],
                [11.5114481, 48.5199406],
                [11.5120927, 48.5233703],
                [11.5123486, 48.5246768],
                [11.5126251, 48.5257446],
                [11.5127623, 48.526149],
                [11.5129764, 48.5266819],
                [11.5133594, 48.5274752],
                [11.5135056, 48.5277453],
                [11.5137446, 48.5281449],
                [11.5141324, 48.5287516],
                [11.5151518, 48.5302769],
                [11.5155119, 48.5308689],
                [11.5159185, 48.5316157],
                [11.5160629, 48.5319164],
                [11.5162798, 48.5324306],
                [11.5164678, 48.5330245],
                [11.5166192, 48.5335956],
                [11.5167318, 48.5342249],
                [11.5167878, 48.5345866],
                [11.5170592, 48.5366558],
                [11.517167, 48.5375906],
                [11.5174044, 48.5391749],
                [11.5174851, 48.539568],
                [11.517561, 48.5398714],
                [11.5178659, 48.5408548],
                [11.5181046, 48.5414197],
                [11.5182259, 48.5416756],
                [11.518435, 48.5420636],
                [11.5186839, 48.5424798],
                [11.5189247, 48.5428572],
                [11.5192341, 48.5432965],
                [11.519712, 48.5439018],
                [11.519902, 48.5441167],
                [11.520391, 48.5446363],
                [11.5206331, 48.5448748],
                [11.5215826, 48.5457629],
                [11.5235004, 48.5475896],
                [11.5249948, 48.5489927],
                [11.5281361, 48.5519787],
                [11.5389353, 48.5621969],
                [11.5420812, 48.5651956],
                [11.5468129, 48.5696592],
                [11.5494571, 48.5721769],
                [11.5545456, 48.5769738],
                [11.5638163, 48.5857459],
                [11.5648136, 48.5867204],
                [11.5653205, 48.5872634],
                [11.5655353, 48.5875103],
                [11.5659066, 48.5879708],
                [11.5662256, 48.5884026],
                [11.566779, 48.5892035],
                [11.5708933, 48.5953393],
                [11.5715343, 48.5963154],
                [11.5720706, 48.5972382],
                [11.572306, 48.5977088],
                [11.5725115, 48.5981896],
                [11.5726858, 48.598673],
                [11.5728934, 48.5993984],
                [11.5730402, 48.600158],
                [11.5731019, 48.6006724],
                [11.5731376, 48.601159],
                [11.5732386, 48.6033075],
                [11.573618, 48.6120559],
                [11.5736806, 48.6130041],
                [11.5741122, 48.6231523],
                [11.5741226, 48.6238597],
                [11.5741108, 48.6242029],
                [11.5740655, 48.6247228],
                [11.5739831, 48.6251668],
                [11.573864, 48.6256288],
                [11.5737857, 48.6258736],
                [11.5736494, 48.6262528],
                [11.573494, 48.6266245],
                [11.5733054, 48.6269988],
                [11.5731028, 48.6273689],
                [11.5726561, 48.6280582],
                [11.5720761, 48.6287747],
                [11.5716017, 48.6292724],
                [11.5709813, 48.6298216],
                [11.5702841, 48.6303678],
                [11.5697315, 48.6307545],
                [11.5694424, 48.6309356],
                [11.5685448, 48.6314523],
                [11.5606461, 48.6355959],
                [11.5597733, 48.6360998],
                [11.5586844, 48.636808],
                [11.5493037, 48.643183],
                [11.5485877, 48.6436504],
                [11.5480294, 48.6439931],
                [11.5474523, 48.6443164],
                [11.5469991, 48.6445503],
                [11.5465308, 48.644777],
                [11.5459999, 48.645007],
                [11.5454291, 48.6452322],
                [11.5445956, 48.6455263],
                [11.5437224, 48.645786],
                [11.5425816, 48.6460711],
                [11.5414178, 48.6463194],
                [11.535526, 48.6475239],
                [11.5251841, 48.6495719],
                [11.4748507, 48.6596578],
                [11.4738164, 48.6598726],
                [11.4725174, 48.6601765],
                [11.4715283, 48.6604449],
                [11.4710408, 48.6605945],
                [11.4703012, 48.6608427],
                [11.4695883, 48.6611073],
                [11.4690708, 48.6613201],
                [11.4680749, 48.6617615],
                [11.467151, 48.6622391],
                [11.4667131, 48.6624894],
                [11.4662893, 48.6627478],
                [11.4657026, 48.6631285],
                [11.4651593, 48.6635154],
                [11.4642678, 48.6642248],
                [11.4636232, 48.6648123],
                [11.4630452, 48.6654199],
                [11.4626722, 48.6658545],
                [11.4622734, 48.6663477],
                [11.4619375, 48.6668341],
                [11.4616317, 48.6673331],
                [11.4613938, 48.6677587],
                [11.4612751, 48.6679966],
                [11.4608322, 48.6691257],
                [11.4606518, 48.6697268],
                [11.4605119, 48.6704432],
                [11.4604485, 48.6708677],
                [11.4603891, 48.6713881],
                [11.4603412, 48.6719423],
                [11.4599556, 48.6779812],
                [11.4598855, 48.6787463],
                [11.4597306, 48.6796101],
                [11.4596327, 48.6800581],
                [11.4591028, 48.6822689],
                [11.458069, 48.6866907],
                [11.4558709, 48.6958908],
                [11.4556203, 48.6968707],
                [11.4555115, 48.6972518],
                [11.4552788, 48.6979891],
                [11.4551554, 48.6983409],
                [11.4504697, 48.7105624],
                [11.4496313, 48.7127795],
                [11.4473266, 48.718743],
                [11.4463841, 48.7212697],
                [11.4454894, 48.7237253],
                [11.4449152, 48.7252534],
                [11.4433226, 48.7292425],
                [11.4431505, 48.7297068],
                [11.4422116, 48.7319998],
                [11.4417647, 48.7331284],
                [11.4374088, 48.7444412]
              ]
            },
            "properties": {
              "id": 0,
              "route_index": 0,
              "from_eva": "8000261",
              "to_eva": "8000183",
              "line": "1",
              "category": "RE",
              "from_name": "München Hbf",
              "to_name": "Ingolstadt Hbf",
              "begin": "2024-10-04T15:10:00Z",
              "end": "2024-10-04T16:01:00Z",
              "estimated_travel_time_total": "PT52M"
            }
          }
        ]
      }
    },
    {
      "alternativeRouteParts": [
        {
          "from": { "evaNumber": "8098263", "name": "München Hbf (tief)" },
          "replacementTransports": [
            {
              "begin": "2024-10-04T18:28:00Z",
              "end": "2024-10-04T19:07:00Z",
              "line": {
                "administrationID": "800725",
                "category": "S",
                "line": "2"
              },
              "type": "UNKNOWN"
            }
          ],
          "to": { "evaNumber": "8004775", "name": "Petershausen(Obb)" }
        },
        {
          "from": { "evaNumber": "8004775", "name": "Petershausen(Obb)" },
          "replacementTransports": [
            {
              "begin": "2024-10-04T19:23:00Z",
              "end": "2024-10-04T20:00:00Z",
              "line": {
                "administrationID": "800765",
                "category": "RE",
                "line": "1"
              },
              "type": "UNKNOWN"
            }
          ],
          "to": { "evaNumber": "8000183", "name": "Ingolstadt Hbf" }
        }
      ],
      "intervals": "Fr 18:25",
      "estimatedTravelTime": 5700.0,
      "headway": null,
      "begin": "2024-10-04T18:25:00Z",
      "end": "2024-10-04T18:25:00Z",
      "geom": {
        "type": "FeatureCollection",
        "features": [
          {
            "type": "Feature",
            "geometry": {
              "type": "LineString",
              "coordinates": [
                [11.5588457, 48.1409162],
                [11.5544205, 48.1412423],
                [11.5537307, 48.1412701],
                [11.5517861, 48.1412606],
                [11.546463, 48.1416627],
                [11.5445274, 48.1418299],
                [11.5397033, 48.1421956],
                [11.5385243, 48.1422741],
                [11.5372982, 48.1423385],
                [11.534628, 48.1424488],
                [11.53039, 48.1425723],
                [11.5298841, 48.1426001],
                [11.5192344536, 48.1433788832],
                [11.5184829, 48.1434151],
                [11.5177697, 48.1434236],
                [11.5170806, 48.1434129],
                [11.5137338, 48.1432722],
                [11.5126055, 48.1432838],
                [11.5117018, 48.1433326],
                [11.5108206, 48.1433983],
                [11.4980989, 48.1447378],
                [11.4953972, 48.1450119],
                [11.4927359, 48.1453352],
                [11.4921554, 48.1454517],
                [11.4915475, 48.1456006],
                [11.4912453, 48.1456906],
                [11.4909565, 48.1457914],
                [11.4903418, 48.1460357],
                [11.489931, 48.146225],
                [11.4893904, 48.1465223],
                [11.4887432, 48.1469485],
                [11.4876514, 48.1476337],
                [11.485475, 48.1495367],
                [11.484459, 48.1503991],
                [11.484101, 48.1507313],
                [11.4838039, 48.1510411],
                [11.4834714, 48.1514254],
                [11.483303, 48.1516406],
                [11.4829764, 48.1521161],
                [11.4825731, 48.1527657],
                [11.4823892, 48.1530952],
                [11.4820397, 48.1537678],
                [11.481819, 48.1542546],
                [11.4816761, 48.1545988],
                [11.4815116, 48.1550699],
                [11.4811456, 48.1562816],
                [11.4808017, 48.1573639],
                [11.4805465312, 48.1580984311],
                [11.48033, 48.1586986],
                [11.4794382, 48.1609692],
                [11.4785667, 48.1634074],
                [11.4782373971, 48.1642703285],
                [11.4778635, 48.1652039],
                [11.4771698, 48.1668303],
                [11.4766476, 48.1680961],
                [11.473772, 48.1754688],
                [11.4729192311, 48.1777226013],
                [11.4717443, 48.1806151],
                [11.4713435, 48.1817551],
                [11.4708502, 48.1832267],
                [11.469955, 48.1859631],
                [11.4694753, 48.1873108],
                [11.4677019, 48.1918038],
                [11.4667488, 48.1941701],
                [11.4664422, 48.1949124],
                [11.4652625, 48.1976066],
                [11.4647396, 48.1988505],
                [11.46396, 48.2007796],
                [11.4628818, 48.2033932],
                [11.4597759667, 48.2112596881],
                [11.458975, 48.2133299],
                [11.4576365, 48.2169731],
                [11.4567785, 48.2191648],
                [11.4551953186, 48.2231632753],
                [11.4532895, 48.2280231],
                [11.4528008, 48.2292269],
                [11.4522503, 48.2305095],
                [11.4515676, 48.232197],
                [11.4475348, 48.2425057],
                [11.4472518, 48.2432824],
                [11.4468406, 48.244572],
                [11.4465661, 48.245556],
                [11.4461932, 48.2470601],
                [11.4460282, 48.2476746],
                [11.4456376, 48.2495954],
                [11.4449549, 48.252856],
                [11.4445187961, 48.2547164079],
                [11.4441865, 48.2560516],
                [11.4437524, 48.257553],
                [11.4428212, 48.2605495],
                [11.4425789, 48.2614196],
                [11.4424471, 48.2619638],
                [11.4423025, 48.2627878],
                [11.4422698, 48.2630541],
                [11.4422297, 48.2635467],
                [11.4422164, 48.2638361],
                [11.4422158, 48.2642068],
                [11.4422281, 48.2645746],
                [11.4422541, 48.2649409],
                [11.4422942, 48.2652816],
                [11.442396, 48.2658983],
                [11.4424487, 48.2661473],
                [11.4426383, 48.266869],
                [11.4430048, 48.268034],
                [11.4439219, 48.2708105],
                [11.4441329, 48.2713891],
                [11.4444616, 48.2721907],
                [11.4446491, 48.2725928],
                [11.4448805, 48.2730324],
                [11.4451856, 48.273551],
                [11.4455223, 48.2740805],
                [11.4459531, 48.2746773],
                [11.4464306, 48.2752604],
                [11.4469428, 48.2758274],
                [11.4474032, 48.2762917],
                [11.4478849, 48.2767455],
                [11.4484022, 48.2772065],
                [11.4511037, 48.2794722],
                [11.4516035, 48.2799211],
                [11.4521016, 48.2803934],
                [11.4527286, 48.281037],
                [11.4532223, 48.2816118],
                [11.4535497, 48.2820262],
                [11.4538642, 48.2824472],
                [11.4542233, 48.2829847],
                [11.4545516, 48.2835321],
                [11.4547303, 48.2838636],
                [11.4550495, 48.2845284],
                [11.4552843, 48.2851077],
                [11.4555054, 48.2857475],
                [11.455682, 48.286392],
                [11.4557958, 48.2869281],
                [11.4558741, 48.287459],
                [11.4559265, 48.287965],
                [11.4559506, 48.2884713],
                [11.4559444, 48.2891459],
                [11.4558954, 48.2897531],
                [11.4558158, 48.2904111],
                [11.4556988162, 48.2911424688],
                [11.4554017, 48.2928511],
                [11.4553367, 48.2932832],
                [11.4552598, 48.2939566],
                [11.4552209, 48.2945803],
                [11.4552266, 48.2955078],
                [11.4552849, 48.2962164],
                [11.4553272, 48.2965568],
                [11.4554623, 48.2973467],
                [11.4561201, 48.3002137],
                [11.4562196, 48.3007325],
                [11.4563066, 48.3014045],
                [11.4563437, 48.3018619],
                [11.4563615, 48.3023165],
                [11.4563592, 48.3029389],
                [11.4563397, 48.3033549],
                [11.4563018, 48.3037683],
                [11.4562431, 48.3042287],
                [11.4561066, 48.3050225],
                [11.4560303, 48.3053551],
                [11.4558281, 48.3060465],
                [11.4556557, 48.306556],
                [11.4554943, 48.3069805],
                [11.4552287, 48.3075769],
                [11.4549478, 48.3081791],
                [11.4546034, 48.3088416],
                [11.4463175, 48.3242819],
                [11.4460117, 48.3249259],
                [11.4458304, 48.3253628],
                [11.445576, 48.3261011],
                [11.4454495, 48.3265521],
                [11.4453807, 48.3268418],
                [11.4452919, 48.3272803],
                [11.4452284, 48.3277242],
                [11.4451391, 48.3288784],
                [11.4450977, 48.3298812],
                [11.4450716, 48.3308929],
                [11.4449927, 48.3326772],
                [11.4445675, 48.3438836],
                [11.4444539, 48.3458656],
                [11.444329, 48.3476988],
                [11.4440793, 48.354043],
                [11.4440078, 48.3560883],
                [11.444042, 48.3568913],
                [11.4440839, 48.3574358],
                [11.4442587, 48.3583705],
                [11.4444188, 48.3589629],
                [11.4448334, 48.3601095],
                [11.4465584, 48.3641668],
                [11.4470688, 48.3653378],
                [11.4473737, 48.3659551],
                [11.4478761, 48.3668339],
                [11.4481879, 48.3672942],
                [11.4486346, 48.3678908],
                [11.4492128, 48.3685698],
                [11.4558339, 48.3758212],
                [11.4582914, 48.3785284],
                [11.4589188, 48.3792682],
                [11.4595192, 48.3800538],
                [11.4599931, 48.3807594],
                [11.4604773, 48.3816135],
                [11.4606951, 48.3820724],
                [11.4608949, 48.3825293],
                [11.4611566, 48.383223],
                [11.461378, 48.3839175],
                [11.4616914, 48.3850197],
                [11.4634845, 48.3917579],
                [11.4636573, 48.3924619],
                [11.4637513, 48.3930292],
                [11.4638237, 48.3935647],
                [11.46387, 48.3941426],
                [11.463882, 48.394629],
                [11.4638473, 48.3954123],
                [11.4632334, 48.401031],
                [11.4631706, 48.4017415],
                [11.4631278, 48.4026113],
                [11.463134, 48.4031923],
                [11.4631521, 48.4035037],
                [11.4631806, 48.4038334],
                [11.4632888, 48.4045789],
                [11.4634713, 48.4053477],
                [11.4635952, 48.4057658],
                [11.4638565, 48.4064671],
                [11.4641485, 48.4071226],
                [11.4644675, 48.4077154],
                [11.4649601, 48.4084947],
                [11.4652158, 48.4088676],
                [11.4658588, 48.4096731],
                [11.4660412, 48.4098859],
                [11.4666412, 48.4105192],
                [11.4670639, 48.4109232],
                [11.4678586, 48.4116174],
                [11.4688149, 48.4123824],
                [11.4699989218, 48.4132964401]
              ]
            },
            "properties": {
              "id": 0,
              "route_index": 0,
              "from_eva": "8098263",
              "to_eva": "8004775",
              "line": "2",
              "category": "S",
              "from_name": "München Hbf (tief)",
              "to_name": "Petershausen(Obb)",
              "begin": "2024-10-04T18:28:00Z",
              "end": "2024-10-04T19:07:00Z",
              "estimated_travel_time_total": "PT1H35M"
            }
          },
          {
            "type": "Feature",
            "geometry": {
              "type": "LineString",
              "coordinates": [
                [11.4699989218, 48.4132964401],
                [11.4717079, 48.4146088],
                [11.4725569, 48.4152964],
                [11.4731152, 48.4157839],
                [11.4737155, 48.4163477],
                [11.4742053, 48.4168589],
                [11.4746896, 48.4174157],
                [11.475104, 48.4179336],
                [11.4754605, 48.4184404],
                [11.4757969, 48.4189528],
                [11.4760552, 48.4193842],
                [11.476283, 48.4198148],
                [11.4764479, 48.420168],
                [11.4766644, 48.4205957],
                [11.4768443, 48.4210156],
                [11.4772524, 48.4221294],
                [11.4774302, 48.4226837],
                [11.4776524, 48.4236155],
                [11.4777156, 48.4239957],
                [11.4777939, 48.4246165],
                [11.4778486, 48.4254699],
                [11.4778891, 48.4270437],
                [11.4779042, 48.4287164],
                [11.4779452, 48.430839],
                [11.4779789, 48.4314398],
                [11.4780451, 48.4320281],
                [11.4781594, 48.4326095],
                [11.478305, 48.4331882],
                [11.4784475, 48.4336145],
                [11.4786052, 48.434046],
                [11.4787006, 48.4342718],
                [11.4789437, 48.4347875],
                [11.4792557, 48.4353759],
                [11.4794871, 48.4357573],
                [11.4797302, 48.4361135],
                [11.4802274, 48.4367838],
                [11.4807791, 48.4374388],
                [11.4810781, 48.4377524],
                [11.4813955, 48.4380686],
                [11.4823137, 48.4388775],
                [11.4832983, 48.4396475],
                [11.4888313, 48.4438186],
                [11.4903644, 48.4449865],
                [11.4910662, 48.4455594],
                [11.4916781, 48.4461079],
                [11.4922377, 48.446678],
                [11.4925897, 48.4470685],
                [11.4929126, 48.4474553],
                [11.493383, 48.448075],
                [11.4953568, 48.4508963],
                [11.4959425, 48.4516411],
                [11.4961297, 48.4518618],
                [11.4965322, 48.4523034],
                [11.4969641, 48.4527456],
                [11.4974388, 48.4531775],
                [11.4982063, 48.4538084],
                [11.4990238, 48.4544115],
                [11.5024095, 48.4566802],
                [11.5031616, 48.4572055],
                [11.5037993, 48.4576897],
                [11.5041724, 48.4579953],
                [11.5047153, 48.4584773],
                [11.5052564, 48.4590087],
                [11.5056927, 48.4594848],
                [11.5060706, 48.4599272],
                [11.5064309, 48.4603874],
                [11.507716, 48.462092],
                [11.5079876, 48.4624664],
                [11.5085065, 48.4632198],
                [11.5088326, 48.4637632],
                [11.5091241, 48.4643078],
                [11.5093216, 48.4647263],
                [11.5095618, 48.465333],
                [11.5097615, 48.465968],
                [11.5098902, 48.4664879],
                [11.5100216, 48.4672003],
                [11.5100845, 48.4679262],
                [11.5101297, 48.4691688],
                [11.5103905, 48.4789459],
                [11.510426, 48.4797626],
                [11.5104815, 48.4803365],
                [11.5105855, 48.4811188],
                [11.5107125, 48.4818488],
                [11.5111543, 48.4838553],
                [11.5113816, 48.4849624],
                [11.5130543, 48.4926118],
                [11.513189, 48.493299],
                [11.5132588, 48.4937899],
                [11.5132944, 48.4941604],
                [11.5133225, 48.4946706],
                [11.5133111, 48.4952688],
                [11.5132758, 48.4956826],
                [11.5132038, 48.4962077],
                [11.5131025, 48.496726],
                [11.5129953, 48.4971359],
                [11.512699, 48.4981465],
                [11.5118573, 48.5008102],
                [11.511336, 48.5025737],
                [11.5107187, 48.5045496],
                [11.5104106, 48.5056293],
                [11.5102595, 48.5062801],
                [11.5101344, 48.5069375],
                [11.5100006, 48.5078294],
                [11.5099368, 48.5084134],
                [11.5098839, 48.5092425],
                [11.5098703, 48.5098483],
                [11.5098894, 48.5108435],
                [11.5099619, 48.5117738],
                [11.5101997, 48.5134177],
                [11.5105196, 48.515147],
                [11.5110271, 48.5178069],
                [11.5114481, 48.5199406],
                [11.5120927, 48.5233703],
                [11.5123486, 48.5246768],
                [11.5126251, 48.5257446],
                [11.5127623, 48.526149],
                [11.5129764, 48.5266819],
                [11.5133594, 48.5274752],
                [11.5135056, 48.5277453],
                [11.5137446, 48.5281449],
                [11.5141324, 48.5287516],
                [11.5151518, 48.5302769],
                [11.5155119, 48.5308689],
                [11.5159185, 48.5316157],
                [11.5160629, 48.5319164],
                [11.5162798, 48.5324306],
                [11.5164678, 48.5330245],
                [11.5166192, 48.5335956],
                [11.5167318, 48.5342249],
                [11.5167878, 48.5345866],
                [11.5170592, 48.5366558],
                [11.517167, 48.5375906],
                [11.5174044, 48.5391749],
                [11.5174851, 48.539568],
                [11.517561, 48.5398714],
                [11.5178659, 48.5408548],
                [11.5181046, 48.5414197],
                [11.5182259, 48.5416756],
                [11.518435, 48.5420636],
                [11.5186839, 48.5424798],
                [11.5189247, 48.5428572],
                [11.5192341, 48.5432965],
                [11.519712, 48.5439018],
                [11.519902, 48.5441167],
                [11.520391, 48.5446363],
                [11.5206331, 48.5448748],
                [11.5215826, 48.5457629],
                [11.5235004, 48.5475896],
                [11.5249948, 48.5489927],
                [11.5281361, 48.5519787],
                [11.5389353, 48.5621969],
                [11.5420812, 48.5651956],
                [11.5468129, 48.5696592],
                [11.5494571, 48.5721769],
                [11.5545456, 48.5769738],
                [11.5638163, 48.5857459],
                [11.5648136, 48.5867204],
                [11.5653205, 48.5872634],
                [11.5655353, 48.5875103],
                [11.5659066, 48.5879708],
                [11.5662256, 48.5884026],
                [11.566779, 48.5892035],
                [11.5708933, 48.5953393],
                [11.5715343, 48.5963154],
                [11.5720706, 48.5972382],
                [11.572306, 48.5977088],
                [11.5725115, 48.5981896],
                [11.5726858, 48.598673],
                [11.5727737, 48.5989644],
                [11.5728934, 48.5993984],
                [11.5729487, 48.5996512],
                [11.5730402, 48.600158],
                [11.5731019, 48.6006724],
                [11.5731376, 48.601159],
                [11.573618, 48.6120559],
                [11.5736806, 48.6130041],
                [11.5741122, 48.6231523],
                [11.5741226, 48.6238597],
                [11.5741108, 48.6242029],
                [11.5740655, 48.6247228],
                [11.5739831, 48.6251668],
                [11.573864, 48.6256288],
                [11.5737857, 48.6258736],
                [11.573575, 48.626439],
                [11.573494, 48.6266245],
                [11.5733054, 48.6269988],
                [11.5731028, 48.6273689],
                [11.5726561, 48.6280582],
                [11.5720761, 48.6287747],
                [11.5716017, 48.6292724],
                [11.5709813, 48.6298216],
                [11.5702841, 48.6303678],
                [11.5697315, 48.6307545],
                [11.5694424, 48.6309356],
                [11.5685448, 48.6314523],
                [11.5606461, 48.6355959],
                [11.5597733, 48.6360998],
                [11.5586844, 48.636808],
                [11.5493037, 48.643183],
                [11.5485877, 48.6436504],
                [11.5480294, 48.6439931],
                [11.5474523, 48.6443164],
                [11.5469991, 48.6445503],
                [11.5465308, 48.644777],
                [11.5459999, 48.645007],
                [11.5454291, 48.6452322],
                [11.5445956, 48.6455263],
                [11.5437224, 48.645786],
                [11.5425816, 48.6460711],
                [11.5414178, 48.6463194],
                [11.535526, 48.6475239],
                [11.5251841, 48.6495719],
                [11.4748507, 48.6596578],
                [11.4738164, 48.6598726],
                [11.4725174, 48.6601765],
                [11.4715283, 48.6604449],
                [11.4710408, 48.6605945],
                [11.4703012, 48.6608427],
                [11.4695883, 48.6611073],
                [11.4690708, 48.6613201],
                [11.4680749, 48.6617615],
                [11.467151, 48.6622391],
                [11.4667131, 48.6624894],
                [11.4662893, 48.6627478],
                [11.4657026, 48.6631285],
                [11.4651593, 48.6635154],
                [11.4642678, 48.6642248],
                [11.4636232, 48.6648123],
                [11.4630452, 48.6654199],
                [11.4626722, 48.6658545],
                [11.4622734, 48.6663477],
                [11.4619375, 48.6668341],
                [11.4616317, 48.6673331],
                [11.4613938, 48.6677587],
                [11.4612751, 48.6679966],
                [11.4608322, 48.6691257],
                [11.4606518, 48.6697268],
                [11.4605119, 48.6704432],
                [11.4604485, 48.6708677],
                [11.4603891, 48.6713881],
                [11.4603412, 48.6719423],
                [11.4599556, 48.6779812],
                [11.4598855, 48.6787463],
                [11.4597306, 48.6796101],
                [11.4596327, 48.6800581],
                [11.4591028, 48.6822689],
                [11.458069, 48.6866907],
                [11.4558709, 48.6958908],
                [11.4556203, 48.6968707],
                [11.4555115, 48.6972518],
                [11.4552788, 48.6979891],
                [11.4551554, 48.6983409],
                [11.4504697, 48.7105624],
                [11.4496313, 48.7127795],
                [11.4473266, 48.718743],
                [11.4463841, 48.7212697],
                [11.4454894, 48.7237253],
                [11.4449152, 48.7252534],
                [11.4433226, 48.7292425],
                [11.4431505, 48.7297068],
                [11.4422116, 48.7319998],
                [11.4417647, 48.7331284],
                [11.4374088, 48.7444412]
              ]
            },
            "properties": {
              "id": 1,
              "route_index": 0,
              "from_eva": "8004775",
              "to_eva": "8000183",
              "line": "1",
              "category": "RE",
              "from_name": "Petershausen(Obb)",
              "to_name": "Ingolstadt Hbf",
              "begin": "2024-10-04T19:23:00Z",
              "end": "2024-10-04T20:00:00Z",
              "estimated_travel_time_total": "PT1H35M"
            }
          }
        ]
      }
    }
  ],
  "demo_metadata": {
    "disrupted_geom": {
      "type": "FeatureCollection",
      "features": [
        {
          "type": "Feature",
          "geometry": {
            "type": "LineString",
            "coordinates": [
              [11.5558051, 48.1414745],
              [11.5534692, 48.141645],
              [11.5501545, 48.1416478],
              [11.5469908, 48.1418817],
              [11.5460811, 48.1419746],
              [11.5451791, 48.1420443],
              [11.5411193, 48.1423439],
              [11.5395187, 48.1424333],
              [11.538016, 48.142504],
              [11.5375682, 48.1425107],
              [11.5359143, 48.1424819],
              [11.5355082, 48.1424865],
              [11.5328491, 48.1425778],
              [11.5324064, 48.1425811],
              [11.5316184, 48.1425473],
              [11.5311354, 48.1425494],
              [11.53039, 48.1425723],
              [11.5298841, 48.1426001],
              [11.5192344536, 48.1433788832],
              [11.5184829, 48.1434151],
              [11.5177697, 48.1434236],
              [11.5170806, 48.1434129],
              [11.5137338, 48.1432722],
              [11.5126055, 48.1432838],
              [11.5117018, 48.1433326],
              [11.5108206, 48.1433983],
              [11.4980989, 48.1447378],
              [11.4953972, 48.1450119],
              [11.4927359, 48.1453352],
              [11.4921554, 48.1454517],
              [11.4915475, 48.1456006],
              [11.4912453, 48.1456906],
              [11.4909565, 48.1457914],
              [11.4903418, 48.1460357],
              [11.489931, 48.146225],
              [11.4893904, 48.1465223],
              [11.4887432, 48.1469485],
              [11.4876514, 48.1476337],
              [11.485475, 48.1495367],
              [11.484459, 48.1503991],
              [11.484101, 48.1507313],
              [11.4838039, 48.1510411],
              [11.4834714, 48.1514254],
              [11.483303, 48.1516406],
              [11.4829764, 48.1521161],
              [11.4825731, 48.1527657],
              [11.4823892, 48.1530952],
              [11.4820397, 48.1537678],
              [11.481819, 48.1542546],
              [11.4816761, 48.1545988],
              [11.4815116, 48.1550699],
              [11.4811456, 48.1562816],
              [11.4808017, 48.1573639],
              [11.4805465312, 48.1580984311],
              [11.48033, 48.1586986],
              [11.4794382, 48.1609692],
              [11.4785667, 48.1634074],
              [11.4782373971, 48.1642703285],
              [11.4778635, 48.1652039],
              [11.4771698, 48.1668303],
              [11.4766476, 48.1680961],
              [11.473772, 48.1754688],
              [11.4729192311, 48.1777226013],
              [11.4717443, 48.1806151],
              [11.4713435, 48.1817551],
              [11.4708502, 48.1832267],
              [11.469955, 48.1859631],
              [11.4694753, 48.1873108],
              [11.4677019, 48.1918038],
              [11.4667488, 48.1941701],
              [11.4664422, 48.1949124],
              [11.4652625, 48.1976066],
              [11.4647396, 48.1988505],
              [11.46396, 48.2007796],
              [11.4628818, 48.2033932],
              [11.4618489, 48.2060249],
              [11.4605231, 48.2093551],
              [11.458975, 48.2133299],
              [11.4576365, 48.2169731],
              [11.4567785, 48.2191648],
              [11.4551953186, 48.2231632753],
              [11.4532895, 48.2280231],
              [11.4528008, 48.2292269],
              [11.4522503, 48.2305095],
              [11.4515676, 48.232197],
              [11.4475348, 48.2425057],
              [11.4472518, 48.2432824],
              [11.4468406, 48.244572],
              [11.4465661, 48.245556],
              [11.4461932, 48.2470601],
              [11.4460282, 48.2476746],
              [11.4456376, 48.2495954],
              [11.4449549, 48.252856],
              [11.4445187961, 48.2547164079],
              [11.4441865, 48.2560516],
              [11.4437524, 48.257553],
              [11.4428212, 48.2605495],
              [11.4425789, 48.2614196],
              [11.4424471, 48.2619638],
              [11.4423025, 48.2627878],
              [11.4422698, 48.2630541],
              [11.4422297, 48.2635467],
              [11.4422164, 48.2638361],
              [11.4422158, 48.2642068],
              [11.4422281, 48.2645746],
              [11.4422541, 48.2649409],
              [11.4422942, 48.2652816],
              [11.442396, 48.2658983],
              [11.4424487, 48.2661473],
              [11.4426383, 48.266869],
              [11.4430048, 48.268034],
              [11.4439219, 48.2708105],
              [11.4441329, 48.2713891],
              [11.4444616, 48.2721907],
              [11.4446491, 48.2725928],
              [11.4448805, 48.2730324],
              [11.4451856, 48.273551],
              [11.4455223, 48.2740805],
              [11.4459531, 48.2746773],
              [11.4464306, 48.2752604],
              [11.4469428, 48.2758274],
              [11.4474032, 48.2762917],
              [11.4478849, 48.2767455],
              [11.4484022, 48.2772065],
              [11.4511037, 48.2794722],
              [11.4516035, 48.2799211],
              [11.4521016, 48.2803934],
              [11.4527286, 48.281037],
              [11.4532223, 48.2816118],
              [11.4535497, 48.2820262],
              [11.4538642, 48.2824472],
              [11.4542233, 48.2829847],
              [11.4545516, 48.2835321],
              [11.4547303, 48.2838636],
              [11.4550495, 48.2845284],
              [11.4552843, 48.2851077],
              [11.4555054, 48.2857475],
              [11.455682, 48.286392],
              [11.4557958, 48.2869281],
              [11.4558741, 48.287459],
              [11.4559265, 48.287965],
              [11.4559506, 48.2884713],
              [11.4559444, 48.2891459],
              [11.4558954, 48.2897531],
              [11.4558158, 48.2904111],
              [11.4556988162, 48.2911424688],
              [11.4554017, 48.2928511],
              [11.4553367, 48.2932832],
              [11.4552598, 48.2939566],
              [11.4552209, 48.2945803],
              [11.4552266, 48.2955078],
              [11.4552849, 48.2962164],
              [11.4553272, 48.2965568],
              [11.4554623, 48.2973467],
              [11.4561201, 48.3002137],
              [11.4562196, 48.3007325],
              [11.4563066, 48.3014045],
              [11.4563437, 48.3018619],
              [11.4563615, 48.3023165],
              [11.4563592, 48.3029389],
              [11.4563397, 48.3033549],
              [11.4563018, 48.3037683],
              [11.4562431, 48.3042287],
              [11.4561066, 48.3050225],
              [11.4560303, 48.3053551],
              [11.4558281, 48.3060465],
              [11.4556557, 48.306556],
              [11.4554943, 48.3069805],
              [11.4552287, 48.3075769],
              [11.4549478, 48.3081791],
              [11.4546034, 48.3088416],
              [11.4463175, 48.3242819],
              [11.4460117, 48.3249259],
              [11.4458304, 48.3253628],
              [11.445576, 48.3261011],
              [11.4454495, 48.3265521],
              [11.4453807, 48.3268418],
              [11.4452919, 48.3272803],
              [11.4452284, 48.3277242],
              [11.4451391, 48.3288784],
              [11.4450977, 48.3298812],
              [11.4450716, 48.3308929],
              [11.4449927, 48.3326772],
              [11.4445675, 48.3438836],
              [11.4444539, 48.3458656],
              [11.444329, 48.3476988],
              [11.4440793, 48.354043],
              [11.4440078, 48.3560883],
              [11.444042, 48.3568913],
              [11.4440839, 48.3574358],
              [11.4442587, 48.3583705],
              [11.4444188, 48.3589629],
              [11.4448334, 48.3601095],
              [11.4465584, 48.3641668],
              [11.4470688, 48.3653378],
              [11.4473737, 48.3659551],
              [11.4478761, 48.3668339],
              [11.4481879, 48.3672942],
              [11.4486346, 48.3678908],
              [11.4492128, 48.3685698],
              [11.4558339, 48.3758212],
              [11.4582914, 48.3785284],
              [11.4589188, 48.3792682],
              [11.4595192, 48.3800538],
              [11.4599931, 48.3807594],
              [11.4604773, 48.3816135],
              [11.4606951, 48.3820724],
              [11.4608949, 48.3825293],
              [11.4611566, 48.383223],
              [11.461378, 48.3839175],
              [11.4616914, 48.3850197],
              [11.4634845, 48.3917579],
              [11.4636573, 48.3924619],
              [11.4637513, 48.3930292],
              [11.4638237, 48.3935647],
              [11.46387, 48.3941426],
              [11.463882, 48.394629],
              [11.4638473, 48.3954123],
              [11.4632334, 48.401031],
              [11.4631706, 48.4017415],
              [11.4631278, 48.4026113],
              [11.463134, 48.4031923],
              [11.4631521, 48.4035037],
              [11.4631806, 48.4038334],
              [11.4632888, 48.4045789],
              [11.4634713, 48.4053477],
              [11.4635952, 48.4057658],
              [11.4638565, 48.4064671],
              [11.4641485, 48.4071226],
              [11.4644675, 48.4077154],
              [11.4649601, 48.4084947],
              [11.4652158, 48.4088676],
              [11.4658588, 48.4096731],
              [11.4660412, 48.4098859],
              [11.4666412, 48.4105192],
              [11.4670639, 48.4109232],
              [11.4678586, 48.4116174],
              [11.4688149, 48.4123824],
              [11.4699989218, 48.4132964401]
            ]
          },
          "properties": {
            "fromEvaNumber": "8000261",
            "toEvaNumber": "8004775",
            "bidirectional": true
          }
        },
        {
          "type": "Feature",
          "geometry": {
            "type": "LineString",
            "coordinates": [
              [11.4699989218, 48.4132964401],
              [11.4688149, 48.4123824],
              [11.4678586, 48.4116174],
              [11.4670639, 48.4109232],
              [11.4666412, 48.4105192],
              [11.4660412, 48.4098859],
              [11.4658588, 48.4096731],
              [11.4652158, 48.4088676],
              [11.4649601, 48.4084947],
              [11.4644675, 48.4077154],
              [11.4641485, 48.4071226],
              [11.4638565, 48.4064671],
              [11.4635952, 48.4057658],
              [11.4634713, 48.4053477],
              [11.4632888, 48.4045789],
              [11.4631806, 48.4038334],
              [11.4631521, 48.4035037],
              [11.463134, 48.4031923],
              [11.4631278, 48.4026113],
              [11.4631706, 48.4017415],
              [11.4632334, 48.401031],
              [11.4638473, 48.3954123],
              [11.463882, 48.394629],
              [11.46387, 48.3941426],
              [11.4638237, 48.3935647],
              [11.4637513, 48.3930292],
              [11.4636573, 48.3924619],
              [11.4634845, 48.3917579],
              [11.4616914, 48.3850197],
              [11.461378, 48.3839175],
              [11.4611566, 48.383223],
              [11.4608949, 48.3825293],
              [11.4606951, 48.3820724],
              [11.4604773, 48.3816135],
              [11.4599931, 48.3807594],
              [11.4595192, 48.3800538],
              [11.4589188, 48.3792682],
              [11.4582914, 48.3785284],
              [11.4558339, 48.3758212],
              [11.4492128, 48.3685698],
              [11.4486346, 48.3678908],
              [11.4481879, 48.3672942],
              [11.4478761, 48.3668339],
              [11.4473737, 48.3659551],
              [11.4470688, 48.3653378],
              [11.4465584, 48.3641668],
              [11.4448334, 48.3601095],
              [11.4444188, 48.3589629],
              [11.4442587, 48.3583705],
              [11.4440839, 48.3574358],
              [11.444042, 48.3568913],
              [11.4440078, 48.3560883],
              [11.4440793, 48.354043],
              [11.444329, 48.3476988],
              [11.4444539, 48.3458656],
              [11.4445675, 48.3438836],
              [11.4449927, 48.3326772],
              [11.4450716, 48.3308929],
              [11.4450977, 48.3298812],
              [11.4451391, 48.3288784],
              [11.4452284, 48.3277242],
              [11.4452919, 48.3272803],
              [11.4453807, 48.3268418],
              [11.4454495, 48.3265521],
              [11.445576, 48.3261011],
              [11.4458304, 48.3253628],
              [11.4460117, 48.3249259],
              [11.4463175, 48.3242819],
              [11.4546034, 48.3088416],
              [11.4549478, 48.3081791],
              [11.4552287, 48.3075769],
              [11.4554943, 48.3069805],
              [11.4556557, 48.306556],
              [11.4558281, 48.3060465],
              [11.4560303, 48.3053551],
              [11.4561066, 48.3050225],
              [11.4562431, 48.3042287],
              [11.4563018, 48.3037683],
              [11.4563397, 48.3033549],
              [11.4563651, 48.3026269],
              [11.4563437, 48.3018619],
              [11.4563066, 48.3014045],
              [11.4562196, 48.3007325],
              [11.4561201, 48.3002137],
              [11.4554623, 48.2973467],
              [11.4553272, 48.2965568],
              [11.4552849, 48.2962164],
              [11.4552266, 48.2955078],
              [11.4552209, 48.2945803],
              [11.4552598, 48.2939566],
              [11.4553367, 48.2932832],
              [11.4554017, 48.2928511],
              [11.4556988162, 48.2911424688],
              [11.4558158, 48.2904111],
              [11.4558954, 48.2897531],
              [11.4559444, 48.2891459],
              [11.4559506, 48.2884713],
              [11.4559265, 48.287965],
              [11.4558741, 48.287459],
              [11.4557958, 48.2869281],
              [11.455682, 48.286392],
              [11.4555054, 48.2857475],
              [11.4552843, 48.2851077],
              [11.4550495, 48.2845284],
              [11.4547303, 48.2838636],
              [11.4545516, 48.2835321],
              [11.4542233, 48.2829847],
              [11.4538642, 48.2824472],
              [11.4535497, 48.2820262],
              [11.4532223, 48.2816118],
              [11.4527286, 48.281037],
              [11.4521016, 48.2803934],
              [11.4516035, 48.2799211],
              [11.4511037, 48.2794722],
              [11.4484022, 48.2772065],
              [11.4478849, 48.2767455],
              [11.4474032, 48.2762917],
              [11.4469428, 48.2758274],
              [11.4464306, 48.2752604],
              [11.4459531, 48.2746773],
              [11.4455223, 48.2740805],
              [11.4451856, 48.273551],
              [11.4448805, 48.2730324],
              [11.4446491, 48.2725928],
              [11.4444616, 48.2721907],
              [11.4441329, 48.2713891],
              [11.4439219, 48.2708105],
              [11.4430048, 48.268034],
              [11.4426383, 48.266869],
              [11.4424487, 48.2661473],
              [11.442396, 48.2658983],
              [11.4422942, 48.2652816],
              [11.4422541, 48.2649409],
              [11.4422281, 48.2645746],
              [11.4422158, 48.2642068],
              [11.4422164, 48.2638361],
              [11.4422297, 48.2635467],
              [11.4422698, 48.2630541],
              [11.4423351, 48.2625737],
              [11.4424471, 48.2619638],
              [11.4425789, 48.2614196],
              [11.4428212, 48.2605495],
              [11.4437524, 48.257553],
              [11.4439773, 48.2567948],
              [11.4441865, 48.2560516],
              [11.4445187961, 48.2547164079]
            ]
          },
          "properties": {
            "fromEvaNumber": "8004775",
            "toEvaNumber": "8001354",
            "bidirectional": true
          }
        }
      ]
    }
  }
}
